alblack52
