Metadata-Version: 2.1
Name: alblack52
Version: 0.0.26
Summary: This is the simplest module for quick work with files.
Author: __token__
Author-email: mihajlovic.aleksa@gmail.com
